suppyress/__init__.py
suppyress/suppyress.py
suppyress-0.1.dist-info/METADATA
suppyress-0.1.dist-info/RECORD
suppyress-0.1.dist-info/WHEEL
suppyress-0.1.dist-info/top_level.txt
