Metadata-Version: 2.1
Name: suppyress
Version: 0.1
Summary: A tiny python library for running code and ignore any errors
Home-page: https://github.com/WYishai/suppyress
Author: Yishai Wiesner
Author-email: wyishai@gmail.com
License: UNKNOWN
Platform: UNKNOWN
Classifier: Development Status :: 5 - Production/Stable
Classifier: Intended Audience :: Developers
Classifier: License :: OSI Approved :: Apache Software License
Classifier: Operating System :: OS Independent
Classifier: Programming Language :: Python :: 2.7
Classifier: Topic :: Software Development :: Libraries :: Python Modules
